anu_ctlab_qemscan_bse_to_zarr3/__init__.py
anu_ctlab_qemscan_bse_to_zarr3/py.typed
anu_ctlab_qemscan_bse_to_zarr3-0.1.1.dist-info/METADATA
anu_ctlab_qemscan_bse_to_zarr3-0.1.1.dist-info/WHEEL
anu_ctlab_qemscan_bse_to_zarr3-0.1.1.dist-info/entry_points.txt
anu_ctlab_qemscan_bse_to_zarr3-0.1.1.dist-info/RECORD
